heavyedge_dataset/__init__.py
heavyedge_dataset-1.1.0.dist-info/licenses/LICENSE
heavyedge_dataset-1.1.0.dist-info/METADATA
heavyedge_dataset-1.1.0.dist-info/WHEEL
heavyedge_dataset-1.1.0.dist-info/top_level.txt
heavyedge_dataset-1.1.0.dist-info/RECORD
