Metadata-Version: 2.4
Name: heavyedge-dataset
Version: 1.1.0
Summary: PyTorch-compatible edge profile dataset API
Author-email: Jisoo Song <jeesoo9595@snu.ac.kr>
License-Expression: MIT
Project-URL: homepage, https://pypi.python.org/pypi/heavyedge-dataset/
Project-URL: source, https://github.com/heavyedge/heavyedge-dataset
Project-URL: documentation, https://heavyedge-dataset.readthedocs.io
Classifier: Development Status :: 5 - Production/Stable
Classifier: Intended Audience :: Science/Research
Classifier: Programming Language :: Python
Classifier: Programming Language :: Python :: 3
Classifier: Programming Language :: Python :: 3.10
Classifier: Programming Language :: Python :: 3.11
Classifier: Programming Language :: Python :: 3.12
Classifier: Programming Language :: Python :: 3 :: Only
Classifier: Topic :: Scientific/Engineering
Classifier: Operating System :: OS Independent
Requires-Python: >=3.10
License-File: LICENSE
Requires-Dist: heavyedge>=1.1.2
Requires-Dist: torch
Provides-Extra: test
Requires-Dist: pytest; extra == "test"
Provides-Extra: doc
Requires-Dist: sphinx; extra == "doc"
Requires-Dist: numpydoc; extra == "doc"
Requires-Dist: pydata_sphinx_theme; extra == "doc"
Requires-Dist: matplotlib; extra == "doc"
Provides-Extra: dev
Requires-Dist: flake8; extra == "dev"
Requires-Dist: black; extra == "dev"
Requires-Dist: isort; extra == "dev"
Requires-Dist: heavyedge-dataset[doc,test]; extra == "dev"
Dynamic: license-file
